raindropio/__init__.py
raindropio/api.py
raindropio/models.py
python_raindropio-0.0.3.dist-info/LICENSE
python_raindropio-0.0.3.dist-info/METADATA
python_raindropio-0.0.3.dist-info/WHEEL
python_raindropio-0.0.3.dist-info/top_level.txt
python_raindropio-0.0.3.dist-info/RECORD
