Metadata-Version: 2.1
Name: python-raindropio
Version: 0.0.3
Summary: UNKNOWN
Home-page: https://github.com/atsuoishimoto/python-raindropio
Author: Atsuo Ishimoto
License: MIT
Project-URL: Source, https://github.com/atsuoishimoto/python-raindropio
Platform: UNKNOWN
Classifier: Programming Language :: Python :: 3
Classifier: Programming Language :: Python :: 3.7
Classifier: Programming Language :: Python :: 3.8
Classifier: Development Status :: 3 - Alpha
Classifier: License :: OSI Approved :: MIT License
Requires-Python: >=3.7
Requires-Dist: requests-oauthlib
Requires-Dist: python-dateutil
Requires-Dist: jashin (>=0.0.6)
Requires-Dist: python-dotenv
Provides-Extra: dev
Requires-Dist: wheel ; extra == 'dev'
Requires-Dist: twine ; extra == 'dev'
Requires-Dist: pytest ; extra == 'dev'
Requires-Dist: mypy ; extra == 'dev'
Requires-Dist: black ; extra == 'dev'
Requires-Dist: flake8 ; extra == 'dev'
Requires-Dist: autoflake ; extra == 'dev'
Requires-Dist: pre-commit ; extra == 'dev'
